kasami/__init__.py
kasami/about.py
kasami/functions.py
kasami/nodes.py
kasami/normalizers.py
kasami/productions.py
kasami/tree.py
kasami/tree_scorer.py
kasami/tests/__init__.py
kasami/tests/make_parses.py
kasami/tests/test_nodes.py
kasami/tests/test_normalizers.py
kasami/tests/test_productions.py
kasami/tests/test_tree.py
kasami/tests/test_tree_scorer.py
kasami-0.0.7.dist-info/DESCRIPTION.rst
kasami-0.0.7.dist-info/METADATA
kasami-0.0.7.dist-info/RECORD
kasami-0.0.7.dist-info/WHEEL
kasami-0.0.7.dist-info/metadata.json
kasami-0.0.7.dist-info/top_level.txt
