Metadata-Version: 2.0
Name: kasami
Version: 0.0.7
Summary: A set of utilities for training probabilistic context-free grammars and scoring new sentences with them.
Home-page: https://github.com/halfak/kasami
Author: Aaron Halfaker
Author-email: aaron.halfaker@gmail.com
License: MIT
Platform: UNKNOWN
Classifier: Development Status :: 3 - Alpha
Classifier: Programming Language :: Python
Classifier: Programming Language :: Python :: 3
Classifier: Topic :: Text Processing :: Linguistic
Classifier: Topic :: Scientific/Engineering :: Information Analysis
Classifier: Intended Audience :: Developers
Classifier: License :: OSI Approved :: MIT License
Classifier: Operating System :: OS Independent
Requires-Dist: deltas
